base_package/__init__.py
base_package/__main__.py
base_package/cli.py
base_package/utils.py
base_package/version.py
base_package-0.1.0a1.dist-info/LICENSE
base_package-0.1.0a1.dist-info/METADATA
base_package-0.1.0a1.dist-info/WHEEL
base_package-0.1.0a1.dist-info/entry_points.txt
base_package-0.1.0a1.dist-info/top_level.txt
base_package-0.1.0a1.dist-info/RECORD
