Metadata-Version: 2.1
Name: base-package
Version: 0.1.0a1
Summary: python package template.
Home-page: https://gitlab.com/a.signz089/base-package
Author: a.Signz
Author-email: a.Signz089@googlemail.com
Maintainer: a.Signz
Maintainer-email: a.Signz089@googlemail.com
License: BSD License
Project-URL: Bug Reports, https://gitlab.com/a.signz089/base-package/issues
Project-URL: Source, https://gitlab.com/a.signz089/base-package.git
Platform: UNKNOWN
Classifier: Development Status :: 2 - Pre-Alpha
Classifier: Intended Audience :: Developers
Classifier: License :: OSI Approved :: BSD License
Classifier: Programming Language :: Python
Classifier: Programming Language :: Python :: 3.6
Classifier: Programming Language :: Python :: 3.7
Classifier: Topic :: Software Development :: Libraries
Requires-Dist: coloredlogs (~=10.0)
Requires-Dist: humanfriendly (~=4.18)
Provides-Extra: dev
Requires-Dist: black (==19.3b0) ; extra == 'dev'
Requires-Dist: flake8 (~=3.7) ; extra == 'dev'
Provides-Extra: docs
Requires-Dist: Sphinx (~=2.1.2) ; extra == 'docs'
Requires-Dist: recommonmark (~=0.4.0) ; extra == 'docs'
Provides-Extra: extra
Provides-Extra: test
Requires-Dist: pytest (~=5.1) ; extra == 'test'
Requires-Dist: pytest-cov (~=2.7) ; extra == 'test'
Requires-Dist: pytest-flake8 (~=1.0) ; extra == 'test'
